data_object/__init__.py
data_object/data_object.py
data_object/exceptions.py
data_object/tests/__init__.py
data_object/tests/test_data_object.py
data_object/tests/test_immutable_data_object.py
data_object-1.5.0.dist-info/DESCRIPTION.rst
data_object-1.5.0.dist-info/METADATA
data_object-1.5.0.dist-info/RECORD
data_object-1.5.0.dist-info/WHEEL
data_object-1.5.0.dist-info/metadata.json
data_object-1.5.0.dist-info/top_level.txt
