Metadata-Version: 2.0
Name: data-object
Version: 1.5.0
Summary: Base class for data objects
Home-page: https://github.com/PawelJ-PL/data_object
Author: Pawel
Author-email: inne.poczta@gmail.com
License: MIT
Keywords: Python data object case class boilerplate dto
Platform: UNKNOWN
Classifier: Development Status :: 5 - Production/Stable
Classifier: Intended Audience :: Developers
Classifier: License :: OSI Approved :: MIT License
Classifier: Programming Language :: Python :: 3 :: Only
Classifier: Topic :: Software Development :: Libraries
Requires-Python: >=3
Provides-Extra: test
Requires-Dist: coverage; extra == 'test'
Requires-Dist: nose; extra == 'test'
Requires-Dist: flake8; extra == 'test'
